pyzhmh/__init__.py
pyzhmh/download.py
pyzhmh/magic.py
pyzhmh/rich.py
python_zhmh-0.0.10.dist-info/LICENSE
python_zhmh-0.0.10.dist-info/METADATA
python_zhmh-0.0.10.dist-info/WHEEL
python_zhmh-0.0.10.dist-info/top_level.txt
python_zhmh-0.0.10.dist-info/RECORD
