Metadata-Version: 2.1
Name: python-zhmh
Version: 0.0.10
Summary: Python Common Command
Home-page: https://github.com/zhmhbest/python-zhmh
Author: zhmh
Author-email: zhmhbest@gmail.com
License: MIT
Platform: UNKNOWN
Classifier: Programming Language :: Python :: 3
Classifier: License :: OSI Approved :: MIT License
Classifier: Operating System :: OS Independent
Requires-Python: >=3
Requires-Dist: requests (>=2.18.0)
